batchphoto/__init__.py
batchphoto/__main__.py
batchphoto/crop/__init__.py
batchphoto/crop/__main__.py
batchphoto/crop/contour.py
batchphoto/crop/face.py
batchphoto/crop/uniform_background.py
batchphoto-0.0.2.dev0.dist-info/DESCRIPTION.rst
batchphoto-0.0.2.dev0.dist-info/METADATA
batchphoto-0.0.2.dev0.dist-info/RECORD
batchphoto-0.0.2.dev0.dist-info/WHEEL
batchphoto-0.0.2.dev0.dist-info/entry_points.txt
batchphoto-0.0.2.dev0.dist-info/metadata.json
batchphoto-0.0.2.dev0.dist-info/top_level.txt
