Metadata-Version: 2.0
Name: batchphoto
Version: 0.0.2.dev0
Summary: Python library for batch processing of photos
Home-page: https://github.com/onlyjus/batchphoto
Author: Justin Weber
Author-email: onlyjus@gmail.com
License: MIT
Download-URL: https://github.com/onlyjus/batchphoto/archive/0.1.tar.gz
Keywords: image processing batch
Platform: any
Classifier: Development Status :: 4 - Beta
Classifier: License :: OSI Approved :: MIT License
Classifier: Natural Language :: English
Classifier: Programming Language :: Python :: 2
Classifier: Programming Language :: Python :: 3
Classifier: Topic :: Multimedia :: Graphics :: Graphics Conversion
